cvmanova/__init__.py
cvmanova/api.py
cvmanova/config.py
cvmanova/contrasts.py
cvmanova/core.py
cvmanova/data.py
cvmanova/io.py
cvmanova/loaders.py
cvmanova/region.py
cvmanova/results.py
cvmanova/searchlight.py
cvmanova/utils.py
cvmanova/estimators/__init__.py
cvmanova/estimators/base.py
cvmanova/estimators/region.py
cvmanova/estimators/searchlight.py
cvmanova-4.0.0.dist-info/METADATA
cvmanova-4.0.0.dist-info/WHEEL
cvmanova-4.0.0.dist-info/top_level.txt
cvmanova-4.0.0.dist-info/RECORD
