Metadata-Version: 2.4
Name: cvmanova
Version: 4.0.0
Summary: Cross-validated MANOVA for fMRI data analysis
Author-email: Carsten Allefeld <carsten.allefeld@gmail.com>
Maintainer-email: Carsten Allefeld <carsten.allefeld@gmail.com>
License: GPL-3.0-or-later
Project-URL: Homepage, https://github.com/allefeld/cvmanova
Project-URL: Documentation, https://github.com/allefeld/cvmanova
Project-URL: Repository, https://github.com/allefeld/cvmanova
Project-URL: Issues, https://github.com/allefeld/cvmanova/issues
Keywords: fMRI,MVPA,multivariate pattern analysis,MANOVA,searchlight,neuroimaging,cross-validation
Classifier: Development Status :: 4 - Beta
Classifier: Intended Audience :: Science/Research
Classifier: License :: OSI Approved :: GNU General Public License v3 or later (GPLv3+)
Classifier: Operating System :: OS Independent
Classifier: Programming Language :: Python :: 3
Classifier: Programming Language :: Python :: 3.9
Classifier: Programming Language :: Python :: 3.10
Classifier: Programming Language :: Python :: 3.11
Classifier: Programming Language :: Python :: 3.12
Classifier: Topic :: Scientific/Engineering :: Medical Science Apps.
Classifier: Topic :: Scientific/Engineering :: Image Processing
Requires-Python: >=3.9
Requires-Dist: numpy>=1.20.0
Requires-Dist: scipy>=1.7.0
Requires-Dist: nibabel>=3.0.0
Requires-Dist: joblib>=1.0.0
Requires-Dist: tqdm>=4.60.0
Provides-Extra: dev
Requires-Dist: pytest>=7.0.0; extra == "dev"
Requires-Dist: pytest-cov>=4.0.0; extra == "dev"
Provides-Extra: test
Requires-Dist: pytest>=7.0.0; extra == "test"
Requires-Dist: requests>=2.25.0; extra == "test"
